{"name": "The Croods", "domestic": "$187,168,425", "revenue": "$587,204,668", "release_date": "March 22, 2013", "genre": "Animation", "runtime": "1 hrs. 38 min.", "mpaa_rating": "PG", "budget": "$135 million", "director": ["https://www.boxofficemojo.com/people/chart/?view=Director&id=kirkdemicco.htm", "https://www.boxofficemojo.com/people/chart/?view=Director&id=chrissanders.htm"], "writer": ["https://www.boxofficemojo.com/people/chart/?view=Writer&id=kirkdemicco.htm", "https://www.boxofficemojo.com/people/chart/?view=Writer&id=chrissanders.htm"], "actor": ["https://www.boxofficemojo.com/people/chart/?view=Actor&id=nicolascage.htm", "https://www.boxofficemojo.com/people/chart/?view=Actor&id=emmastone.htm", "https://www.boxofficemojo.com/people/chart/?view=Actor&id=ryanreynolds.htm", "https://www.boxofficemojo.com/people/chart/?view=Actor&id=clarkduke.htm"], "producer": ["https://www.boxofficemojo.com/people/chart/?view=Producer&id=kristinebelson.htm", "https://www.boxofficemojo.com/people/chart/?view=Producer&id=janehartwell.htm"], "composer": "https://www.boxofficemojo.com/people/chart/?view=Director&id=kirkdemicco.htm"}