{"name": "The Hobbit: The Battle of the Five Armies", "domestic": "$255,119,788", "revenue": "$956,019,788", "release_date": "December 17, 2014", "genre": "Fantasy", "runtime": "2 hrs. 24 min.", "mpaa_rating": "PG-13", "budget": "N/A", "director": ["https://www.boxofficemojo.com/people/chart/?view=Director&id=peterjackson.htm"], "writer": ["https://www.boxofficemojo.com/people/chart/?view=Writer&id=philippaboyens.htm", "https://www.boxofficemojo.com/people/chart/?view=Writer&id=guillermodeltoro.htm", "https://www.boxofficemojo.com/people/chart/?view=Writer&id=peterjackson.htm", "https://www.boxofficemojo.com/people/chart/?view=Writer&id=franwalsh.htm"], "actor": ["https://www.boxofficemojo.com/people/chart/?view=Actor&id=ianmckellen.htm", "https://www.boxofficemojo.com/people/chart/?view=Actor&id=martinfreeman.htm", "https://www.boxofficemojo.com/people/chart/?view=Actor&id=lukeevans.htm", "https://www.boxofficemojo.com/people/chart/?view=Actor&id=orlandobloom.htm", "https://www.boxofficemojo.com/people/chart/?view=Actor&id=evangelinelilly.htm"], "producer": ["https://www.boxofficemojo.com/people/chart/?view=Producer&id=peterjackson.htm", "https://www.boxofficemojo.com/people/chart/?view=Producer&id=franwalsh.htm"], "composer": "https://www.boxofficemojo.com/people/chart/?view=Director&id=peterjackson.htm"}