{"name": "Spider-Man", "domestic": "$403,706,375", "revenue": "$821,708,551", "release_date": "May 3, 2002", "genre": "Action / Adventure", "runtime": "2 hrs. 1 min.", "mpaa_rating": "PG-13", "budget": "$139 million", "director": ["https://www.boxofficemojo.com/people/chart/?view=Director&id=samraimi.htm"], "writer": ["https://www.boxofficemojo.com/people/chart/?view=Writer&id=davidkoepp.htm"], "actor": ["https://www.boxofficemojo.com/people/chart/?view=Actor&id=tobeymaguire.htm", "https://www.boxofficemojo.com/people/chart/?view=Actor&id=willemdafoe.htm", "https://www.boxofficemojo.com/people/chart/?view=Actor&id=kirstendunst.htm", "https://www.boxofficemojo.com/people/chart/?view=Actor&id=jamesfranco.htm", "https://www.boxofficemojo.com/people/chart/?view=Actor&id=elizabethbanks.htm"], "producer": ["https://www.boxofficemojo.com/people/chart/?view=Producer&id=ianbryce.htm", "https://www.boxofficemojo.com/people/chart/?view=Producer&id=stanlee.htm", "https://www.boxofficemojo.com/people/chart/?view=Producer&id=lauraziskin.htm", "https://www.boxofficemojo.com/people/chart/?view=Producer&id=aviarad.htm"], "composer": "https://www.boxofficemojo.com/people/chart/?view=Director&id=samraimi.htm"}