{"id": "badlieutenant09", "name": "Bad Lieutenant: Port of Call New Orleans", "domestic": "$1,702,112", "revenue": "$10,589,102", "release_date": "November 20, 2009", "genre": "Crime Drama", "runtime": "2 hrs. 1 min.", "mpaa_rating": "R", "budget": "$25 million", "director": ["https://www.boxofficemojo.com/people/chart/?view=Director&id=wernerherzog.htm"], "writer": ["https://www.boxofficemojo.com/people/chart/?view=Actor&id=nicolascage.htm", "https://www.boxofficemojo.com/people/chart/?view=Actor&id=evamendes.htm", "https://www.boxofficemojo.com/people/chart/?view=Actor&id=valkilmer.htm"], "actor": ["https://www.boxofficemojo.com/people/chart/?view=Producer&id=nicolascage.htm", "https://www.boxofficemojo.com/people/chart/?view=Producer&id=randallemmett.htm", "https://www.boxofficemojo.com/people/chart/?view=Producer&id=georgefurla.htm"], "producer": ["https://www.boxofficemojo.com/people/chart/?view=Composer&id=markisham.htm"], "lastseen": "-", "composer": "https://www.boxofficemojo.com/people/chart/?view=Director&id=wernerherzog.htm"}