{"id": "bedazzled", "name": "Bedazzled (2000)", "domestic": "$37,886,980", "revenue": "$90,383,208", "release_date": "October 20, 2000", "genre": "Fantasy Comedy", "runtime": "1 hrs. 33 min.", "mpaa_rating": "PG-13", "budget": "$48 million", "director": ["https://www.boxofficemojo.com/people/chart/?view=Director&id=haroldramis.htm"], "writer": ["https://www.boxofficemojo.com/people/chart/?view=Writer&id=haroldramis.htm", "https://www.boxofficemojo.com/people/chart/?view=Writer&id=petertolan.htm"], "actor": ["https://www.boxofficemojo.com/people/chart/?view=Actor&id=brendanfraser.htm"], "producer": ["https://www.boxofficemojo.com/people/chart/?view=Cinematographer&id=billpope.htm"], "lastseen": "-", "composer": "https://www.boxofficemojo.com/people/chart/?view=Director&id=haroldramis.htm"}