{"id": "blackdahlia", "name": "The Black Dahlia", "domestic": "$22,545,080", "revenue": "$49,332,692", "release_date": "September 15, 2006", "genre": "Crime Drama", "runtime": "1 hrs. 59 min.", "mpaa_rating": "R", "budget": "$50 million", "director": ["https://www.boxofficemojo.com/people/chart/?view=Director&id=briandepalma.htm"], "writer": ["https://www.boxofficemojo.com/people/chart/?view=Actor&id=joshhartnett.htm", "https://www.boxofficemojo.com/people/chart/?view=Actor&id=scarlettjohansson.htm", "https://www.boxofficemojo.com/people/chart/?view=Actor&id=aaroneckhart.htm", "https://www.boxofficemojo.com/people/chart/?view=Actor&id=hilaryswank.htm"], "actor": ["https://www.boxofficemojo.com/people/chart/?view=Composer&id=markisham.htm"], "producer": [], "lastseen": "-", "composer": "-"}