{"id": "bulletproof", "name": "Bulletproof", "domestic": "$21,576,954", "revenue": "$22,611,954", "release_date": "September 6, 1996", "genre": "Action Comedy", "runtime": "1 hrs. 25 min.", "mpaa_rating": "R", "budget": "N/A", "director": ["https://www.boxofficemojo.com/people/chart/?view=Director&id=ernestdickerson.htm"], "writer": ["https://www.boxofficemojo.com/people/chart/?view=Writer&id=lewiscolick.htm"], "actor": ["https://www.boxofficemojo.com/people/chart/?view=Actor&id=damonwayans.htm", "https://www.boxofficemojo.com/people/chart/?view=Actor&id=adamsandler.htm"], "producer": ["https://www.boxofficemojo.com/people/chart/?view=Producer&id=bradgrey.htm", "https://www.boxofficemojo.com/people/chart/?view=Producer&id=robertsimonds.htm"], "lastseen": "-", "composer": "https://www.boxofficemojo.com/people/chart/?view=Director&id=ernestdickerson.htm"}