{"id": "dccab", "name": "D.C. Cab", "domestic": "$16,134,627", "revenue": "-", "release_date": "December 16, 1983", "genre": "Comedy", "runtime": "1 hrs. 40 min.", "mpaa_rating": "R", "budget": "N/A", "director": ["https://www.boxofficemojo.com/people/chart/?view=Director&id=joelschumacher.htm"], "writer": ["https://www.boxofficemojo.com/people/chart/?view=Producer&id=jonpeters.htm"], "actor": ["https://www.boxofficemojo.com/people/chart/?view=Cinematographer&id=deancundey.htm"], "producer": [], "lastseen": "-", "composer": "-"}