{"id": "dcfilm1117", "name": "Justice League", "domestic": "$229,024,295", "revenue": "$657,924,295", "release_date": "November 17, 2017", "genre": "Action / Adventure", "runtime": "1 hrs. 59 min.", "mpaa_rating": "PG-13", "budget": "N/A", "director": ["https://www.boxofficemojo.com/people/chart/?view=Director&id=zacksnyder.htm"], "writer": ["https://www.boxofficemojo.com/people/chart/?view=Writer&id=christerrio.htm", "https://www.boxofficemojo.com/people/chart/?view=Writer&id=josswhedon.htm"], "actor": ["https://www.boxofficemojo.com/people/chart/?view=Actor&id=benaffleck.htm", "https://www.boxofficemojo.com/people/chart/?view=Actor&id=henrycavill.htm", "https://www.boxofficemojo.com/people/chart/?view=Actor&id=galgadot.htm", "https://www.boxofficemojo.com/people/chart/?view=Actor&id=jasonmomoa.htm", "https://www.boxofficemojo.com/people/chart/?view=Actor&id=ezramiller.htm"], "producer": ["https://www.boxofficemojo.com/people/chart/?view=Composer&id=dannyelfman.htm"], "lastseen": "-", "composer": "https://www.boxofficemojo.com/people/chart/?view=Director&id=zacksnyder.htm"}