{"id": "dieanotherday", "name": "Die Another Day", "domestic": "$160,942,139", "revenue": "$431,971,116", "release_date": "November 22, 2002", "genre": "Action", "runtime": "2 hrs. 3 min.", "mpaa_rating": "PG-13", "budget": "$142 million", "director": ["https://www.boxofficemojo.com/people/chart/?view=Director&id=leetamahori.htm"], "writer": ["https://www.boxofficemojo.com/people/chart/?view=Writer&id=nealpurvis.htm", "https://www.boxofficemojo.com/people/chart/?view=Writer&id=robertwade.htm"], "actor": ["https://www.boxofficemojo.com/people/chart/?view=Actor&id=rosamundpike.htm", "https://www.boxofficemojo.com/people/chart/?view=Actor&id=piercebrosnan.htm", "https://www.boxofficemojo.com/people/chart/?view=Actor&id=halleberry.htm", "https://www.boxofficemojo.com/people/chart/?view=Actor&id=judidench.htm", "https://www.boxofficemojo.com/people/chart/?view=Actor&id=madonna.htm"], "producer": ["https://www.boxofficemojo.com/people/chart/?view=Producer&id=barbarabroccoli.htm", "https://www.boxofficemojo.com/people/chart/?view=Producer&id=michaelgwilson.htm"], "lastseen": "-", "composer": null}