{"id": "disneyfairytale2017", "name": "Disney's Christopher Robin", "domestic": "$99,215,042", "revenue": "$197,374,532", "release_date": "August 3, 2018", "genre": "Fantasy", "runtime": "1 hrs. 44 min.", "mpaa_rating": "PG", "budget": "$75 million", "director": ["https://www.boxofficemojo.com/people/chart/?view=Director&id=marcforster.htm"], "writer": ["https://www.boxofficemojo.com/people/chart/?view=Writer&id=tommccarthy.htm", "https://www.boxofficemojo.com/people/chart/?view=Writer&id=alexrossperry.htm"], "actor": ["https://www.boxofficemojo.com/people/chart/?view=Actor&id=ewanmcgregor.htm"], "producer": ["https://www.boxofficemojo.com/people/chart/?view=Composer&id=jonbrion.htm", "https://www.boxofficemojo.com/people/chart/?view=Composer&id=geoffzanelli.htm"], "lastseen": "-", "composer": "https://www.boxofficemojo.com/people/chart/?view=Director&id=marcforster.htm"}