{"id": "doadeadoralive", "name": "DOA: Dead or Alive", "domestic": "$480,813", "revenue": "$7,516,532", "release_date": "June 15, 2007", "genre": "Action", "runtime": "1 hrs. 26 min.", "mpaa_rating": "PG-13", "budget": "N/A", "director": ["https://www.boxofficemojo.com/people/chart/?view=Writer&id=jflawton.htm"], "writer": ["https://www.boxofficemojo.com/people/chart/?view=Producer&id=paulwsanderson.htm", "https://www.boxofficemojo.com/people/chart/?view=Producer&id=jeremybolt.htm", "https://www.boxofficemojo.com/people/chart/?view=Producer&id=berndeichinger.htm", "https://www.boxofficemojo.com/people/chart/?view=Producer&id=robertkulzer.htm"], "actor": ["https://www.boxofficemojo.com/people/chart/?view=Composer&id=junkiexl.htm"], "producer": [], "lastseen": "-", "composer": "https://www.boxofficemojo.com/people/chart/?view=Writer&id=jflawton.htm"}