{"id": "doomsday", "name": "Doomsday", "domestic": "$11,008,770", "revenue": "$22,211,426", "release_date": "March 14, 2008", "genre": "Sci-Fi Horror", "runtime": "1 hrs. 45 min.", "mpaa_rating": "R", "budget": "N/A", "director": [], "writer": [], "actor": [], "producer": ["https://www.boxofficemojo.com/people/chart/?view=Producer&id=marcdevans.htm", "https://www.boxofficemojo.com/people/chart/?view=Producer&id=trevormacy.htm", "https://www.boxofficemojo.com/people/chart/?view=Producer&id=stevenpaul.htm"], "lastseen": "-", "composer": "-"}