{"id": "fatalattraction", "name": "Fatal Attraction", "domestic": "$156,645,693", "revenue": "$320,145,693", "release_date": "September 18, 1987", "genre": "Thriller", "runtime": "2 hrs. 3 min.", "mpaa_rating": "R", "budget": "N/A", "director": ["https://www.boxofficemojo.com/people/chart/?view=Actor&id=michaeldouglas.htm", "https://www.boxofficemojo.com/people/chart/?view=Actor&id=glennclose.htm"], "writer": ["https://www.boxofficemojo.com/people/chart/?view=Producer&id=sherrylansing.htm"], "actor": [], "producer": [], "lastseen": "-", "composer": "-"}