{"id": "goodboy", "name": "Good Boy!", "domestic": "$37,667,746", "revenue": "$45,312,217", "release_date": "October 10, 2003", "genre": "Family Comedy", "runtime": "1 hrs. 36 min.", "mpaa_rating": "PG", "budget": "$18 million", "director": ["https://www.boxofficemojo.com/people/chart/?view=Actor&id=matthewbroderick.htm"], "writer": ["https://www.boxofficemojo.com/people/chart/?view=Producer&id=stephanieallain.htm", "https://www.boxofficemojo.com/people/chart/?view=Producer&id=kristinebelson.htm"], "actor": ["https://www.boxofficemojo.com/people/chart/?view=Composer&id=markmothersbaugh.htm"], "producer": [], "lastseen": "-", "composer": "https://www.boxofficemojo.com/people/chart/?view=Actor&id=matthewbroderick.htm"}