{"id": "iceman2013", "name": "The Iceman (2013)", "domestic": "$1,969,193", "revenue": "$1,969,193", "release_date": "May 3, 2013", "genre": "Thriller", "runtime": "1 hrs. 45 min.", "mpaa_rating": "R", "budget": "N/A", "director": ["https://www.boxofficemojo.com/people/chart/?view=Actor&id=michaelshannon.htm", "https://www.boxofficemojo.com/people/chart/?view=Actor&id=winonaryder.htm", "https://www.boxofficemojo.com/people/chart/?view=Actor&id=jamesfranco.htm", "https://www.boxofficemojo.com/people/chart/?view=Actor&id=chrisevans.htm"], "writer": [], "actor": [], "producer": [], "lastseen": "-", "composer": "https://www.boxofficemojo.com/people/chart/?view=Actor&id=michaelshannon.htm"}