{"id": "indianajones4", "name": "Indiana Jones and the Kingdom of the Crystal Skull", "domestic": "$317,101,119", "revenue": "$786,636,033", "release_date": "May 22, 2008", "genre": "Period Adventure", "runtime": "2 hrs. 0 min.", "mpaa_rating": "PG-13", "budget": "$185 million", "director": ["https://www.boxofficemojo.com/people/chart/?view=Director&id=stevenspielberg.htm"], "writer": ["https://www.boxofficemojo.com/people/chart/?view=Writer&id=davidkoepp.htm", "https://www.boxofficemojo.com/people/chart/?view=Writer&id=georgelucas.htm", "https://www.boxofficemojo.com/people/chart/?view=Writer&id=jeffnathanson.htm"], "actor": ["https://www.boxofficemojo.com/people/chart/?view=Actor&id=harrisonford.htm", "https://www.boxofficemojo.com/people/chart/?view=Actor&id=cateblanchett.htm", "https://www.boxofficemojo.com/people/chart/?view=Actor&id=shialabeouf.htm", "https://www.boxofficemojo.com/people/chart/?view=Actor&id=jimbroadbent.htm"], "producer": ["https://www.boxofficemojo.com/people/chart/?view=Producer&id=georgelucas.htm", "https://www.boxofficemojo.com/people/chart/?view=Producer&id=frankmarshall.htm"], "lastseen": "-", "composer": "https://www.boxofficemojo.com/people/chart/?view=Director&id=stevenspielberg.htm"}