{"id": "invasion", "name": "The Invasion", "domestic": "$15,074,191", "revenue": "$40,170,558", "release_date": "August 17, 2007", "genre": "Sci-Fi Thriller", "runtime": "1 hrs. 33 min.", "mpaa_rating": "PG-13", "budget": "$80 million", "director": ["https://www.boxofficemojo.com/people/chart/?view=Actor&id=jeffreywright.htm", "https://www.boxofficemojo.com/people/chart/?view=Actor&id=nicolekidman.htm", "https://www.boxofficemojo.com/people/chart/?view=Actor&id=danielcraig.htm"], "writer": ["https://www.boxofficemojo.com/people/chart/?view=Producer&id=dougdavison.htm", "https://www.boxofficemojo.com/people/chart/?view=Producer&id=susandowney.htm", "https://www.boxofficemojo.com/people/chart/?view=Producer&id=roylee.htm", "https://www.boxofficemojo.com/people/chart/?view=Producer&id=joelsilver.htm"], "actor": ["https://www.boxofficemojo.com/people/chart/?view=Composer&id=johnottman.htm"], "producer": [], "lastseen": "-", "composer": "https://www.boxofficemojo.com/people/chart/?view=Actor&id=jeffreywright.htm"}