{"id": "k-9", "name": "K-9", "domestic": "$43,247,647", "revenue": "$78,247,647", "release_date": "April 28, 1989", "genre": "Action Comedy", "runtime": "1 hrs. 41 min.", "mpaa_rating": "PG-13", "budget": "N/A", "director": ["https://www.boxofficemojo.com/people/chart/?view=Producer&id=lawrencegordon.htm", "https://www.boxofficemojo.com/people/chart/?view=Producer&id=lloydlevin.htm"], "writer": ["https://www.boxofficemojo.com/people/chart/?view=Cinematographer&id=deansemler.htm"], "actor": [], "producer": [], "lastseen": "-", "composer": "-"}