{"id": "lotlikelove", "name": "A Lot Like Love", "domestic": "$21,845,719", "revenue": "$42,886,719", "release_date": "April 22, 2005", "genre": "Romantic Comedy", "runtime": "1 hrs. 37 min.", "mpaa_rating": "PG-13", "budget": "$30 million", "director": ["https://www.boxofficemojo.com/people/chart/?view=Actor&id=ashtonkutcher.htm", "https://www.boxofficemojo.com/people/chart/?view=Actor&id=amandapeet.htm", "https://www.boxofficemojo.com/people/chart/?view=Actor&id=alilarter.htm", "https://www.boxofficemojo.com/people/chart/?view=Actor&id=kalpenn.htm"], "writer": ["https://www.boxofficemojo.com/people/chart/?view=Cinematographer&id=johndeborman.htm"], "actor": ["https://www.boxofficemojo.com/people/chart/?view=Composer&id=alexwurman.htm"], "producer": [], "lastseen": "-", "composer": "-"}