{"id": "mybestfriendsgirl", "name": "My Best Friend's Girl", "domestic": "$19,219,250", "revenue": "$41,622,502", "release_date": "September 19, 2008", "genre": "Romantic Comedy", "runtime": "1 hrs. 41 min.", "mpaa_rating": "R", "budget": "$20 million", "director": [], "writer": ["https://www.boxofficemojo.com/people/chart/?view=Actor&id=katehudson.htm", "https://www.boxofficemojo.com/people/chart/?view=Actor&id=alecbaldwin.htm"], "actor": ["https://www.boxofficemojo.com/people/chart/?view=Cinematographer&id=jackngreen.htm"], "producer": ["https://www.boxofficemojo.com/people/chart/?view=Composer&id=johndebney.htm"], "lastseen": "-", "composer": "-"}