{"id": "rumorhasit", "name": "Rumor Has It", "domestic": "$43,000,262", "revenue": "$88,933,562", "release_date": "December 25, 2005", "genre": "Romantic Comedy", "runtime": "1 hrs. 36 min.", "mpaa_rating": "PG-13", "budget": "N/A", "director": ["https://www.boxofficemojo.com/people/chart/?view=Director&id=robreiner.htm"], "writer": ["https://www.boxofficemojo.com/people/chart/?view=Writer&id=tedgriffin.htm"], "actor": ["https://www.boxofficemojo.com/people/chart/?view=Actor&id=mikevogel.htm", "https://www.boxofficemojo.com/people/chart/?view=Actor&id=jenniferaniston.htm", "https://www.boxofficemojo.com/people/chart/?view=Actor&id=kevincostner.htm", "https://www.boxofficemojo.com/people/chart/?view=Actor&id=markruffalo.htm", "https://www.boxofficemojo.com/people/chart/?view=Actor&id=kathybates.htm"], "producer": ["https://www.boxofficemojo.com/people/chart/?view=Producer&id=jenniferfox.htm", "https://www.boxofficemojo.com/people/chart/?view=Producer&id=stevensoderbergh.htm"], "lastseen": "-", "composer": "https://www.boxofficemojo.com/people/chart/?view=Director&id=robreiner.htm"}