{"id": "selma", "name": "Selma", "domestic": "$52,076,908", "revenue": "$66,787,908", "release_date": "December 25, 2014", "genre": "Drama", "runtime": "2 hrs. 7 min.", "mpaa_rating": "PG-13", "budget": "$20 million", "director": ["https://www.boxofficemojo.com/people/chart/?view=Director&id=avaduvernay.htm"], "writer": ["https://www.boxofficemojo.com/people/chart/?view=Writer&id=paulwebb.htm"], "actor": ["https://www.boxofficemojo.com/people/chart/?view=Actor&id=lakeithstanfield.htm", "https://www.boxofficemojo.com/people/chart/?view=Actor&id=tessathompson.htm", "https://www.boxofficemojo.com/people/chart/?view=Actor&id=davidoyelowo.htm", "https://www.boxofficemojo.com/people/chart/?view=Actor&id=tomwilkinson.htm", "https://www.boxofficemojo.com/people/chart/?view=Actor&id=giovanniribisi.htm"], "producer": ["https://www.boxofficemojo.com/people/chart/?view=Producer&id=avaduvernay.htm", "https://www.boxofficemojo.com/people/chart/?view=Producer&id=dedegardner.htm", "https://www.boxofficemojo.com/people/chart/?view=Producer&id=jeremykleiner.htm", "https://www.boxofficemojo.com/people/chart/?view=Producer&id=bradpitt.htm", "https://www.boxofficemojo.com/people/chart/?view=Producer&id=oprahwinfrey.htm"], "lastseen": "-", "composer": "https://www.boxofficemojo.com/people/chart/?view=Director&id=avaduvernay.htm"}