{"id": "skyhigh", "name": "Sky High", "domestic": "$63,946,815", "revenue": "$86,369,815", "release_date": "July 29, 2005", "genre": "Family Adventure", "runtime": "1 hrs. 42 min.", "mpaa_rating": "PG", "budget": "$35 million", "director": ["https://www.boxofficemojo.com/people/chart/?view=Director&id=mikemitchell.htm"], "writer": ["https://www.boxofficemojo.com/people/chart/?view=Actor&id=kurtrussell.htm", "https://www.boxofficemojo.com/people/chart/?view=Actor&id=maryelizabethwinstead.htm", "https://www.boxofficemojo.com/people/chart/?view=Actor&id=dustiningram.htm"], "actor": ["https://www.boxofficemojo.com/people/chart/?view=Composer&id=michaelgiacchino.htm"], "producer": [], "lastseen": "-", "composer": "-"}