{"id": "thelittleprince", "name": "The Little Prince", "domestic": "$1,339,152", "revenue": "$97,571,250", "release_date": "February 12, 2016", "genre": "Animation", "runtime": "1 hrs. 48 min.", "mpaa_rating": "PG", "budget": "N/A", "director": ["https://www.boxofficemojo.com/people/chart/?view=Composer&id=richardharvey.htm", "https://www.boxofficemojo.com/people/chart/?view=Composer&id=hanszimmer.htm"], "writer": [], "actor": [], "producer": [], "lastseen": "Jun. 12, 2016:", "composer": "https://www.boxofficemojo.com/people/chart/?view=Composer&id=richardharvey.htm"}